<?xml version="1.0" encoding="UTF-8"?>
<!-- Created by  Svyatoslav Urbanovych surban@bigmir.net  svyatoslav.urbanovych@gmail.com-->

<GENERAL 
	id="guide.4.2"
	type_document="%EXECUTEBEAN.SYSTEM:Request.getParameter(java.lang.String:'$type')%" 
	orientation="portrait"
	LIB="%EXECUTEBEAN.SYSTEM:Request.getParameter(java.lang.String:'$lib')%"
	>
	<STYLE  id="STYLE_FOOTER"
			font = "helvetica"
			font_size = "15"
			font_type = "bold"			
			font_color_rgb = "200,200,150"				
			align = "left"
	/>
	
	<PAGE_FOOTER PAGE_N="TRUE" STYLE_id="STYLE_FOOTER">footer</PAGE_FOOTER>
	<INIT>
		<object_java id="test" method="java.lang.String(java.lang.String:'vub - .. CORPORATE  (PROVA)')"/>
		<object_java id="dx_bu2" method="java.lang.String(java.lang.String:'%EXECUTEBEAN.test.toString()%')"/>
	
		<object_java 	id="counter" 
				type="java.math.BigDecimal" 
				class="java.math.BigDecimal" 
				source="" 
				method="java.math.BigDecimal(java.lang.String:'1')"/>	
		<object_java 	id="max" 
						type="java.math.BigDecimal" 
						class="java.math.BigDecimal" 
						source="" 
				method="java.math.BigDecimal(java.lang.String:'11')"/>
		
		<object_java id="data" type="java.util.Date" class="java.util.Date" source="" method=""/>
		<object_java id="s_d_f" type="java.text.SimpleDateFormat" class="java.text.SimpleDateFormat" source="" method="java.text.SimpleDateFormat(java.lang.String:'dd/MM/yy')"/>
		
		
		

		<STYLE id="STYLE_1"
				font = "helvetica"
				font_size = "12"
				font_type = "bold"			
							
				align = "left"
		/>
	
		<STYLE id="ST_CELL_H" FONT="HELVETICA" FONT_SIZE="10" BORDER="15" ALIGN="CENTER" BORDER_COLOR_RGB="250,10,170"/>
		
	</INIT>
	<DOCUMENT>
		<PAGE_HEADER>
			
			<usebean id="s_d_f" method="applyPattern(STRING:yyyy-MM-dd)" SET=""/>

			<PARAGRAPH>
				<PHRASE STYLE_id="STYLE_1">data - %EXECUTEBEAN.s_d_f.format(java.util.Date:data)%</PHRASE>	
			</PARAGRAPH>
			<BLOCK STYLE_id="STYLE_1">counter initial = %EXECUTEBEAN.counter.toString()%</BLOCK>
		
		</PAGE_HEADER>
		
	<CONDITION_FOR FOR_FIRSTCOUNTER="0" FOR_LASTCOUNTER="%EXECUTEBEAN.max.toString()%" id="condition1" FOR_STEPCOUNTER="1"/>			
	
		<TABLE COL="4" COLLS_DIMENTION="25,25,25,25">
	<CYCLE id="cycle1" CONDITION_id="condition1" CONDITION_type="CONDITION_FOR">
	
			<TABLE_ROW>
				<table_cell STYLE_id="ST_CELL_H">cell 1 index cycle = %EXECUTETAG.CONDITION_FOR:condition1.RETURN.INDEX%</table_cell>
		<usebean id="counter" method="add(java.math.BigDecimal:2)" SET="counter"/>	
				<table_cell STYLE_id="ST_CELL_H">cell 2 counter +2 = %EXECUTEBEAN.counter.toString()% </table_cell>
		<object_java 	id="bigDecimal2" type="java.math.BigDecimal" class="java.math.BigDecimal" source="" method="java.math.BigDecimal(java.lang.String:'2')"/>	
		<usebean id="counter" method="add(java.math.BigDecimal:[bigDecimal2])" SET="counter"/>
				<table_cell STYLE_id="ST_CELL_H">cell 3 counter +4 = %EXECUTEBEAN.counter.toString()% </table_cell>
				
				<table_cell STYLE_id="ST_CELL_H">%EXECUTEBEAN.dx_bu2.toString()%</table_cell>
			</TABLE_ROW>		
	</CYCLE>	
		</TABLE>	
		
		
<IMAGE IMAGE_source="/neoHort/images/logo_small.gif" ABSOLUTE_X="20" ABSOLUTE_Y="20"/>	
	</DOCUMENT>
</GENERAL>
